shipyard/__init__.py
shipyard/client.py
shipyard/filesystem.py
shipyard/python.py
shipyard/session.py
shipyard/shell.py
shipyard/types.py
shipyard/utils.py
shipyard_python_sdk-0.2.3.dist-info/METADATA
shipyard_python_sdk-0.2.3.dist-info/WHEEL
shipyard_python_sdk-0.2.3.dist-info/top_level.txt
shipyard_python_sdk-0.2.3.dist-info/RECORD
