Metadata-Version: 2.4
Name: shipyard-python-sdk
Version: 0.2.3
Summary: Shipyard Python SDK is an agent sandbox sdk
Requires-Python: >=3.10
Requires-Dist: aiohttp>=3.12.15
Requires-Dist: filetype>=1.2.0
